czi2ometiff/__init__.py
czi2ometiff/converter.py
czi2ometiff-0.1.0.dist-info/LICENSE
czi2ometiff-0.1.0.dist-info/METADATA
czi2ometiff-0.1.0.dist-info/WHEEL
czi2ometiff-0.1.0.dist-info/top_level.txt
czi2ometiff-0.1.0.dist-info/RECORD
