Metadata-Version: 2.1
Name: czi2ometiff
Version: 0.1.0
Summary: Convert czi to OME-TIFF
Home-page: https://github.com/TristanWhitmarsh/czi2ometiff
Author: Tristan Whitmarsh
Author-email: tw401@cam.ac.uk
License: UNKNOWN
Platform: UNKNOWN
Classifier: Development Status :: 3 - Alpha
Classifier: Intended Audience :: Science/Research
Classifier: License :: OSI Approved :: BSD License
Classifier: Programming Language :: Python :: 3
Classifier: Topic :: Scientific/Engineering :: Bio-Informatics
Requires-Python: >=3.6
License-File: LICENSE
Requires-Dist: numpy (>=1.20)
Requires-Dist: czifile (>=2019.7.2)
Requires-Dist: numpy2ometiff (>=0.1.0)
